[
  {
    "id": "T20260130122505",
    "cycle": 3,
    "action": "BUY",
    "direction": "BULLISH",
    "entry_price": 1.1968,
    "entry_time": "2026-01-30T12:25:05.920962",
    "optimal_tp": 1.1976,
    "optimal_sl": 1.1963000000000001,
    "tp_distance_pips": 7,
    "sl_distance_pips": 4,
    "trade_size": 1000.0,
    "confidence": 65.0,
    "status": "CLOSED",
    "result": "PARTIAL_FAIL",
    "exit_price": 1.1968,
    "exit_time": "2026-01-30T12:27:06.214463",
    "exit_reason": "\u23f0 TIME ENDED at breakeven (TP NOT HIT)",
    "profit_pips": 0.0,
    "profit_amount": 0.0,
    "duration_seconds": 120.293489,
    "max_profit_pips": 0,
    "max_loss_pips": 0,
    "reason": "Strong 2-min BULLISH signal (65.0% confidence)",
    "cycle_duration": 120,
    "ml_used": false,
    "ml_training_samples": 0,
    "volatility": 0.00015,
    "win_rate": 0.0,
    "git_pushed": false
  },
  {
    "id": "T20260130122505",
    "cycle": 3,
    "action": "BUY",
    "direction": "BULLISH",
    "entry_price": 1.1968,
    "entry_time": "2026-01-30T12:25:05.920962",
    "optimal_tp": 1.1976,
    "optimal_sl": 1.1963000000000001,
    "tp_distance_pips": 7,
    "sl_distance_pips": 4,
    "trade_size": 1000.0,
    "confidence": 65.0,
    "status": "CLOSED",
    "result": "PARTIAL_FAIL",
    "exit_price": 1.1968,
    "exit_time": "2026-01-30T12:27:06.214463",
    "exit_reason": "\u23f0 TIME ENDED at breakeven (TP NOT HIT)",
    "profit_pips": 0.0,
    "profit_amount": 0.0,
    "duration_seconds": 120.293489,
    "max_profit_pips": 0,
    "max_loss_pips": 0,
    "reason": "Strong 2-min BULLISH signal (65.0% confidence)",
    "cycle_duration": 120,
    "ml_used": false,
    "ml_training_samples": 0,
    "volatility": 0.00015,
    "win_rate": 0.0,
    "git_pushed": true
  },
  {
    "id": "T20260130122707",
    "cycle": 4,
    "action": "BUY",
    "direction": "BULLISH",
    "entry_price": 1.1968,
    "entry_time": "2026-01-30T12:27:07.170020",
    "optimal_tp": 1.1976,
    "optimal_sl": 1.1963000000000001,
    "tp_distance_pips": 7,
    "sl_distance_pips": 4,
    "trade_size": 1000.0,
    "confidence": 95.0,
    "status": "CLOSED",
    "result": "PARTIAL_FAIL",
    "exit_price": 1.1968,
    "exit_time": "2026-01-30T12:31:07.210941",
    "exit_reason": "\u23f0 TIME ENDED at breakeven (TP NOT HIT)",
    "profit_pips": 0.0,
    "profit_amount": 0.0,
    "duration_seconds": 240.040909,
    "max_profit_pips": 0,
    "max_loss_pips": 0,
    "reason": "Strong 2-min BULLISH signal (95.0% confidence)",
    "cycle_duration": 120,
    "ml_used": false,
    "ml_training_samples": 1,
    "volatility": 0.00015,
    "win_rate": 0.0,
    "git_pushed": false
  },
  {
    "id": "T20260130122707",
    "cycle": 4,
    "action": "BUY",
    "direction": "BULLISH",
    "entry_price": 1.1968,
    "entry_time": "2026-01-30T12:27:07.170020",
    "optimal_tp": 1.1976,
    "optimal_sl": 1.1963000000000001,
    "tp_distance_pips": 7,
    "sl_distance_pips": 4,
    "trade_size": 1000.0,
    "confidence": 95.0,
    "status": "CLOSED",
    "result": "PARTIAL_FAIL",
    "exit_price": 1.1968,
    "exit_time": "2026-01-30T12:31:07.210941",
    "exit_reason": "\u23f0 TIME ENDED at breakeven (TP NOT HIT)",
    "profit_pips": 0.0,
    "profit_amount": 0.0,
    "duration_seconds": 240.040909,
    "max_profit_pips": 0,
    "max_loss_pips": 0,
    "reason": "Strong 2-min BULLISH signal (95.0% confidence)",
    "cycle_duration": 120,
    "ml_used": false,
    "ml_training_samples": 1,
    "volatility": 0.00015,
    "win_rate": 0.0,
    "git_pushed": true
  },
  {
    "id": "T20260130123908",
    "cycle": 10,
    "action": "BUY",
    "direction": "BULLISH",
    "entry_price": 1.1968,
    "entry_time": "2026-01-30T12:39:08.323344",
    "optimal_tp": 1.1976,
    "optimal_sl": 1.1963000000000001,
    "tp_distance_pips": 7,
    "sl_distance_pips": 4,
    "trade_size": 1000.0,
    "confidence": 95.0,
    "status": "CLOSED",
    "result": "PARTIAL_FAIL",
    "exit_price": 1.1968,
    "exit_time": "2026-01-30T12:41:08.710620",
    "exit_reason": "\u23f0 TIME ENDED at breakeven (TP NOT HIT)",
    "profit_pips": 0.0,
    "profit_amount": 0.0,
    "duration_seconds": 120.38726,
    "max_profit_pips": 0,
    "max_loss_pips": 0,
    "reason": "Strong 2-min BULLISH signal (95.0% confidence)",
    "cycle_duration": 120,
    "ml_used": false,
    "ml_training_samples": 2,
    "volatility": 0.00015,
    "win_rate": 0.0,
    "git_pushed": false
  },
  {
    "id": "T20260130123908",
    "cycle": 10,
    "action": "BUY",
    "direction": "BULLISH",
    "entry_price": 1.1968,
    "entry_time": "2026-01-30T12:39:08.323344",
    "optimal_tp": 1.1976,
    "optimal_sl": 1.1963000000000001,
    "tp_distance_pips": 7,
    "sl_distance_pips": 4,
    "trade_size": 1000.0,
    "confidence": 95.0,
    "status": "CLOSED",
    "result": "PARTIAL_FAIL",
    "exit_price": 1.1968,
    "exit_time": "2026-01-30T12:41:08.710620",
    "exit_reason": "\u23f0 TIME ENDED at breakeven (TP NOT HIT)",
    "profit_pips": 0.0,
    "profit_amount": 0.0,
    "duration_seconds": 120.38726,
    "max_profit_pips": 0,
    "max_loss_pips": 0,
    "reason": "Strong 2-min BULLISH signal (95.0% confidence)",
    "cycle_duration": 120,
    "ml_used": false,
    "ml_training_samples": 2,
    "volatility": 0.00015,
    "win_rate": 0.0,
    "git_pushed": true
  },
  {
    "id": "T20260130124109",
    "cycle": 11,
    "action": "BUY",
    "direction": "BULLISH",
    "entry_price": 1.1968,
    "entry_time": "2026-01-30T12:41:09.694648",
    "optimal_tp": 1.1976,
    "optimal_sl": 1.1963000000000001,
    "tp_distance_pips": 7,
    "sl_distance_pips": 4,
    "trade_size": 1000.0,
    "confidence": 65.0,
    "status": "CLOSED",
    "result": "PARTIAL_FAIL",
    "exit_price": 1.1968,
    "exit_time": "2026-01-30T12:45:09.223150",
    "exit_reason": "\u23f0 TIME ENDED at breakeven (TP NOT HIT)",
    "profit_pips": 0.0,
    "profit_amount": 0.0,
    "duration_seconds": 239.528492,
    "max_profit_pips": 0,
    "max_loss_pips": 0,
    "reason": "Strong 2-min BULLISH signal (65.0% confidence)",
    "cycle_duration": 120,
    "ml_used": false,
    "ml_training_samples": 3,
    "volatility": 0.00015,
    "win_rate": 0.0,
    "git_pushed": false
  },
  {
    "id": "T20260130124109",
    "cycle": 11,
    "action": "BUY",
    "direction": "BULLISH",
    "entry_price": 1.1968,
    "entry_time": "2026-01-30T12:41:09.694648",
    "optimal_tp": 1.1976,
    "optimal_sl": 1.1963000000000001,
    "tp_distance_pips": 7,
    "sl_distance_pips": 4,
    "trade_size": 1000.0,
    "confidence": 65.0,
    "status": "CLOSED",
    "result": "PARTIAL_FAIL",
    "exit_price": 1.1968,
    "exit_time": "2026-01-30T12:45:09.223150",
    "exit_reason": "\u23f0 TIME ENDED at breakeven (TP NOT HIT)",
    "profit_pips": 0.0,
    "profit_amount": 0.0,
    "duration_seconds": 239.528492,
    "max_profit_pips": 0,
    "max_loss_pips": 0,
    "reason": "Strong 2-min BULLISH signal (65.0% confidence)",
    "cycle_duration": 120,
    "ml_used": false,
    "ml_training_samples": 3,
    "volatility": 0.00015,
    "win_rate": 0.0,
    "git_pushed": true
  },
  {
    "id": "T20260130124709",
    "cycle": 14,
    "action": "BUY",
    "direction": "BULLISH",
    "entry_price": 1.1968,
    "entry_time": "2026-01-30T12:47:09.608621",
    "optimal_tp": 1.1976,
    "optimal_sl": 1.1963000000000001,
    "tp_distance_pips": 7,
    "sl_distance_pips": 4,
    "trade_size": 1000.0,
    "confidence": 65.0,
    "status": "CLOSED",
    "result": "PARTIAL_FAIL",
    "exit_price": 1.1968,
    "exit_time": "2026-01-30T12:49:09.911029",
    "exit_reason": "\u23f0 TIME ENDED at breakeven (TP NOT HIT)",
    "profit_pips": 0.0,
    "profit_amount": 0.0,
    "duration_seconds": 120.302393,
    "max_profit_pips": 0,
    "max_loss_pips": 0,
    "reason": "Strong 2-min BULLISH signal (65.0% confidence)",
    "cycle_duration": 120,
    "ml_used": false,
    "ml_training_samples": 4,
    "volatility": 0.00015,
    "win_rate": 0.0,
    "git_pushed": false
  },
  {
    "id": "T20260130124709",
    "cycle": 14,
    "action": "BUY",
    "direction": "BULLISH",
    "entry_price": 1.1968,
    "entry_time": "2026-01-30T12:47:09.608621",
    "optimal_tp": 1.1976,
    "optimal_sl": 1.1963000000000001,
    "tp_distance_pips": 7,
    "sl_distance_pips": 4,
    "trade_size": 1000.0,
    "confidence": 65.0,
    "status": "CLOSED",
    "result": "PARTIAL_FAIL",
    "exit_price": 1.1968,
    "exit_time": "2026-01-30T12:49:09.911029",
    "exit_reason": "\u23f0 TIME ENDED at breakeven (TP NOT HIT)",
    "profit_pips": 0.0,
    "profit_amount": 0.0,
    "duration_seconds": 120.302393,
    "max_profit_pips": 0,
    "max_loss_pips": 0,
    "reason": "Strong 2-min BULLISH signal (65.0% confidence)",
    "cycle_duration": 120,
    "ml_used": false,
    "ml_training_samples": 4,
    "volatility": 0.00015,
    "win_rate": 0.0,
    "git_pushed": true
  },
  {
    "id": "T1",
    "cycle": 1,
    "action": "SELL",
    "direction": "BEARISH",
    "entry_price": 1.0849974869844268,
    "entry_time": "2026-01-30T13:04:56.239415",
    "optimal_tp": 1.0841974869844269,
    "optimal_sl": 1.0854974869844267,
    "tp_distance_pips": 7,
    "sl_distance_pips": 4,
    "trade_size": 1000.0,
    "confidence": 67.77777777777779,
    "status": "CLOSED",
    "result": "FAILED",
    "exit_price": 1.1968,
    "exit_time": "2026-01-30T13:06:18.440386",
    "exit_reason": "\u274c SL HIT! -4 pips loss in 82.2s",
    "profit_pips": -1118.0251301557332,
    "profit_amount": -111.80251301557333,
    "duration_seconds": 82.200953,
    "max_profit_pips": 0,
    "max_loss_pips": -1118.0251301557332,
    "reason": "Strong 2-min BEARISH signal (67.8% confidence)",
    "cycle_duration": 120,
    "ml_used": true,
    "ml_training_samples": 10,
    "volatility": 0.00015,
    "win_rate": 0.0,
    "git_pushed": false
  },
  {
    "id": "T2",
    "cycle": 1,
    "action": "BUY",
    "direction": "BULLISH",
    "entry_price": 1.0849925075775124,
    "entry_time": "2026-01-30T13:12:53.759621",
    "optimal_tp": 1.0857925075775123,
    "optimal_sl": 1.0844925075775125,
    "tp_distance_pips": 7,
    "sl_distance_pips": 4,
    "trade_size": 1000.0,
    "confidence": 95.0,
    "status": "CLOSED",
    "result": "SUCCESS",
    "exit_price": 1.1968,
    "exit_time": "2026-01-30T13:14:18.451829",
    "exit_reason": "TP HIT! +7 pips in 84.7s",
    "profit_pips": 1118.0749242248767,
    "profit_amount": 111.80749242248767,
    "duration_seconds": 84.692185,
    "max_profit_pips": 1118.0749242248767,
    "max_loss_pips": 0,
    "reason": "Strong 2-min BULLISH signal (95.0% confidence)",
    "cycle_duration": 120,
    "ml_used": true,
    "ml_training_samples": 11,
    "volatility": 0.00015,
    "win_rate": 0.0,
    "git_pushed": false
  },
  {
    "id": "T3",
    "cycle": 3,
    "action": "SELL",
    "direction": "BEARISH",
    "entry_price": 1.1968,
    "entry_time": "2026-01-30T13:16:17.459370",
    "optimal_tp": 1.1960000000000002,
    "optimal_sl": 1.1973,
    "tp_distance_pips": 7,
    "sl_distance_pips": 4,
    "trade_size": 1000.0,
    "confidence": 95.0,
    "status": "CLOSED",
    "result": "PARTIAL_FAIL",
    "exit_price": 1.1968,
    "exit_time": "2026-01-30T13:18:17.753452",
    "exit_reason": "\u23f0 TIME ENDED at breakeven (TP NOT HIT)",
    "profit_pips": 0.0,
    "profit_amount": 0.0,
    "duration_seconds": 120.294065,
    "max_profit_pips": 0,
    "max_loss_pips": 0,
    "reason": "Strong 2-min BEARISH signal (95.0% confidence)",
    "cycle_duration": 120,
    "ml_used": true,
    "ml_training_samples": 12,
    "volatility": 0.00015,
    "win_rate": 8.333333333333332,
    "git_pushed": false
  },
  {
    "id": "T4",
    "cycle": 4,
    "action": "SELL",
    "direction": "BEARISH",
    "entry_price": 1.1968,
    "entry_time": "2026-01-30T13:18:18.774481",
    "optimal_tp": 1.1960000000000002,
    "optimal_sl": 1.1973,
    "tp_distance_pips": 7,
    "sl_distance_pips": 4,
    "trade_size": 1000.0,
    "confidence": 95.0,
    "status": "CLOSED",
    "result": "PARTIAL_FAIL",
    "exit_price": 1.1968,
    "exit_time": "2026-01-30T13:22:18.263949",
    "exit_reason": "\u23f0 TIME ENDED at breakeven (TP NOT HIT)",
    "profit_pips": 0.0,
    "profit_amount": 0.0,
    "duration_seconds": 239.489455,
    "max_profit_pips": 0,
    "max_loss_pips": 0,
    "reason": "Strong 2-min BEARISH signal (95.0% confidence)",
    "cycle_duration": 120,
    "ml_used": true,
    "ml_training_samples": 13,
    "volatility": 0.00015,
    "win_rate": 7.6923076923076925,
    "git_pushed": false
  },
  {
    "id": "T5",
    "cycle": 6,
    "action": "SELL",
    "direction": "BEARISH",
    "entry_price": 1.1968,
    "entry_time": "2026-01-30T13:22:19.391688",
    "optimal_tp": 1.1960000000000002,
    "optimal_sl": 1.1973,
    "tp_distance_pips": 7,
    "sl_distance_pips": 4,
    "trade_size": 1000.0,
    "confidence": 95.0,
    "status": "CLOSED",
    "result": "PARTIAL_FAIL",
    "exit_price": 1.1968,
    "exit_time": "2026-01-30T13:26:18.961605",
    "exit_reason": "\u23f0 TIME ENDED at breakeven (TP NOT HIT)",
    "profit_pips": 0.0,
    "profit_amount": 0.0,
    "duration_seconds": 239.569904,
    "max_profit_pips": 0,
    "max_loss_pips": 0,
    "reason": "Strong 2-min BEARISH signal (95.0% confidence)",
    "cycle_duration": 120,
    "ml_used": true,
    "ml_training_samples": 14,
    "volatility": 0.00015,
    "win_rate": 7.142857142857142,
    "git_pushed": false
  },
  {
    "id": "T6",
    "cycle": 8,
    "action": "SELL",
    "direction": "BEARISH",
    "entry_price": 1.1968,
    "entry_time": "2026-01-30T13:26:20.758599",
    "optimal_tp": 1.1960000000000002,
    "optimal_sl": 1.1973,
    "tp_distance_pips": 7,
    "sl_distance_pips": 4,
    "trade_size": 1000.0,
    "confidence": 95.0,
    "status": "CLOSED",
    "result": "PARTIAL_FAIL",
    "exit_price": 1.1968,
    "exit_time": "2026-01-30T13:30:19.263305",
    "exit_reason": "\u23f0 TIME ENDED at breakeven (TP NOT HIT)",
    "profit_pips": 0.0,
    "profit_amount": 0.0,
    "duration_seconds": 238.504691,
    "max_profit_pips": 0,
    "max_loss_pips": 0,
    "reason": "Strong 2-min BEARISH signal (95.0% confidence)",
    "cycle_duration": 120,
    "ml_used": true,
    "ml_training_samples": 15,
    "volatility": 0.00015,
    "win_rate": 6.666666666666667,
    "git_pushed": false
  },
  {
    "id": "T7",
    "cycle": 10,
    "action": "SELL",
    "direction": "BEARISH",
    "entry_price": 1.1968,
    "entry_time": "2026-01-30T13:30:20.312587",
    "optimal_tp": 1.1960000000000002,
    "optimal_sl": 1.1973,
    "tp_distance_pips": 7,
    "sl_distance_pips": 4,
    "trade_size": 1000.0,
    "confidence": 95.0,
    "status": "CLOSED",
    "result": "PARTIAL_FAIL",
    "exit_price": 1.1968,
    "exit_time": "2026-01-30T13:34:19.761863",
    "exit_reason": "\u23f0 TIME ENDED at breakeven (TP NOT HIT)",
    "profit_pips": 0.0,
    "profit_amount": 0.0,
    "duration_seconds": 239.449263,
    "max_profit_pips": 0,
    "max_loss_pips": 0,
    "reason": "Strong 2-min BEARISH signal (95.0% confidence)",
    "cycle_duration": 120,
    "ml_used": true,
    "ml_training_samples": 16,
    "volatility": 0.00015,
    "win_rate": 6.25,
    "git_pushed": false
  },
  {
    "id": "T8",
    "cycle": 13,
    "action": "BUY",
    "direction": "BULLISH",
    "entry_price": 1.1968,
    "entry_time": "2026-01-30T13:36:20.055560",
    "optimal_tp": 1.1976,
    "optimal_sl": 1.1963000000000001,
    "tp_distance_pips": 7,
    "sl_distance_pips": 4,
    "trade_size": 1000.0,
    "confidence": 95.0,
    "status": "CLOSED",
    "result": "PARTIAL_FAIL",
    "exit_price": 1.1968,
    "exit_time": "2026-01-30T13:38:20.458678",
    "exit_reason": "\u23f0 TIME ENDED at breakeven (TP NOT HIT)",
    "profit_pips": 0.0,
    "profit_amount": 0.0,
    "duration_seconds": 120.403104,
    "max_profit_pips": 0,
    "max_loss_pips": 0,
    "reason": "Strong 2-min BULLISH signal (95.0% confidence)",
    "cycle_duration": 120,
    "ml_used": true,
    "ml_training_samples": 17,
    "volatility": 0.00015,
    "win_rate": 5.88235294117647,
    "git_pushed": false
  },
  {
    "id": "T9",
    "cycle": 14,
    "action": "SELL",
    "direction": "BEARISH",
    "entry_price": 1.1968,
    "entry_time": "2026-01-30T13:38:22.152214",
    "optimal_tp": 1.1960000000000002,
    "optimal_sl": 1.1973,
    "tp_distance_pips": 7,
    "sl_distance_pips": 4,
    "trade_size": 1000.0,
    "confidence": 67.77777777777779,
    "status": "CLOSED",
    "result": "PARTIAL_FAIL",
    "exit_price": 1.1968,
    "exit_time": "2026-01-30T13:42:20.663342",
    "exit_reason": "\u23f0 TIME ENDED at breakeven (TP NOT HIT)",
    "profit_pips": 0.0,
    "profit_amount": 0.0,
    "duration_seconds": 238.511115,
    "max_profit_pips": 0,
    "max_loss_pips": 0,
    "reason": "Strong 2-min BEARISH signal (67.8% confidence)",
    "cycle_duration": 120,
    "ml_used": true,
    "ml_training_samples": 18,
    "volatility": 0.00015,
    "win_rate": 5.555555555555555,
    "git_pushed": false
  },
  {
    "id": "T10",
    "cycle": 16,
    "action": "BUY",
    "direction": "BULLISH",
    "entry_price": 1.1968,
    "entry_time": "2026-01-30T13:42:21.636485",
    "optimal_tp": 1.1976,
    "optimal_sl": 1.1963000000000001,
    "tp_distance_pips": 7,
    "sl_distance_pips": 4,
    "trade_size": 1000.0,
    "confidence": 95.0,
    "status": "CLOSED",
    "result": "PARTIAL_FAIL",
    "exit_price": 1.1968,
    "exit_time": "2026-01-30T13:46:21.251473",
    "exit_reason": "\u23f0 TIME ENDED at breakeven (TP NOT HIT)",
    "profit_pips": 0.0,
    "profit_amount": 0.0,
    "duration_seconds": 239.614974,
    "max_profit_pips": 0,
    "max_loss_pips": 0,
    "reason": "Strong 2-min BULLISH signal (95.0% confidence)",
    "cycle_duration": 120,
    "ml_used": true,
    "ml_training_samples": 19,
    "volatility": 0.00015,
    "win_rate": 5.263157894736842,
    "git_pushed": false
  },
  {
    "id": "T11",
    "cycle": 18,
    "action": "BUY",
    "direction": "BULLISH",
    "entry_price": 1.1968,
    "entry_time": "2026-01-30T13:46:22.209436",
    "optimal_tp": 1.1976,
    "optimal_sl": 1.1963000000000001,
    "tp_distance_pips": 7,
    "sl_distance_pips": 4,
    "trade_size": 1000.0,
    "confidence": 95.0,
    "status": "CLOSED",
    "result": "PARTIAL_FAIL",
    "exit_price": 1.1968,
    "exit_time": "2026-01-30T13:50:21.757065",
    "exit_reason": "\u23f0 TIME ENDED at breakeven (TP NOT HIT)",
    "profit_pips": 0.0,
    "profit_amount": 0.0,
    "duration_seconds": 239.547617,
    "max_profit_pips": 0,
    "max_loss_pips": 0,
    "reason": "Strong 2-min BULLISH signal (95.0% confidence)",
    "cycle_duration": 120,
    "ml_used": true,
    "ml_training_samples": 20,
    "volatility": 0.00015,
    "win_rate": 5.0,
    "git_pushed": false
  },
  {
    "id": "T12",
    "cycle": 20,
    "action": "BUY",
    "direction": "BULLISH",
    "entry_price": 1.1968,
    "entry_time": "2026-01-30T13:50:23.552738",
    "optimal_tp": 1.1976,
    "optimal_sl": 1.1963000000000001,
    "tp_distance_pips": 7,
    "sl_distance_pips": 4,
    "trade_size": 1000.0,
    "confidence": 95.0,
    "status": "CLOSED",
    "result": "PARTIAL_FAIL",
    "exit_price": 1.1968,
    "exit_time": "2026-01-30T13:54:22.162178",
    "exit_reason": "\u23f0 TIME ENDED at breakeven (TP NOT HIT)",
    "profit_pips": 0.0,
    "profit_amount": 0.0,
    "duration_seconds": 238.609428,
    "max_profit_pips": 0,
    "max_loss_pips": 0,
    "reason": "Strong 2-min BULLISH signal (95.0% confidence)",
    "cycle_duration": 120,
    "ml_used": true,
    "ml_training_samples": 21,
    "volatility": 0.00015,
    "win_rate": 4.761904761904762,
    "git_pushed": false
  },
  {
    "id": "T13",
    "cycle": 22,
    "action": "SELL",
    "direction": "BEARISH",
    "entry_price": 1.1968,
    "entry_time": "2026-01-30T13:54:23.285095",
    "optimal_tp": 1.1960000000000002,
    "optimal_sl": 1.1973,
    "tp_distance_pips": 7,
    "sl_distance_pips": 4,
    "trade_size": 1000.0,
    "confidence": 95.0,
    "status": "CLOSED",
    "result": "PARTIAL_FAIL",
    "exit_price": 1.1968,
    "exit_time": "2026-01-30T13:58:22.857837",
    "exit_reason": "\u23f0 TIME ENDED at breakeven (TP NOT HIT)",
    "profit_pips": 0.0,
    "profit_amount": 0.0,
    "duration_seconds": 239.572727,
    "max_profit_pips": 0,
    "max_loss_pips": 0,
    "reason": "Strong 2-min BEARISH signal (95.0% confidence)",
    "cycle_duration": 120,
    "ml_used": true,
    "ml_training_samples": 22,
    "volatility": 0.00015,
    "win_rate": 4.545454545454546,
    "git_pushed": false
  },
  {
    "id": "T14",
    "cycle": 1,
    "action": "SELL",
    "direction": "BEARISH",
    "entry_price": 1.0849928097591528,
    "entry_time": "2026-01-30T15:25:48.734436",
    "optimal_tp": 1.0841928097591529,
    "optimal_sl": 1.0854928097591527,
    "tp_distance_pips": 7,
    "sl_distance_pips": 4,
    "trade_size": 1000.0,
    "confidence": 67.77777777777779,
    "status": "CLOSED",
    "result": "FAILED",
    "exit_price": 1.1919,
    "exit_time": "2026-01-30T15:27:08.136947",
    "exit_reason": "\u274c SL HIT! -4 pips loss in 79.4s",
    "profit_pips": -1069.0719024084717,
    "profit_amount": -106.90719024084717,
    "duration_seconds": 79.402488,
    "max_profit_pips": 0,
    "max_loss_pips": -1069.0719024084717,
    "reason": "Strong 2-min BEARISH signal (67.8% confidence)",
    "cycle_duration": 120,
    "ml_used": true,
    "ml_training_samples": 23,
    "volatility": 0.00015,
    "win_rate": 4.3478260869565215,
    "git_pushed": false
  },
  {
    "id": "T15",
    "cycle": 2,
    "action": "SELL",
    "direction": "BEARISH",
    "entry_price": 1.1919,
    "entry_time": "2026-01-30T15:27:10.146080",
    "optimal_tp": 1.1911,
    "optimal_sl": 1.1924,
    "tp_distance_pips": 7,
    "sl_distance_pips": 4,
    "trade_size": 1000.0,
    "confidence": 95.0,
    "status": "CLOSED",
    "result": "PARTIAL_FAIL",
    "exit_price": 1.1919,
    "exit_time": "2026-01-30T15:31:08.741579",
    "exit_reason": "\u23f0 TIME ENDED at breakeven (TP NOT HIT)",
    "profit_pips": 0.0,
    "profit_amount": 0.0,
    "duration_seconds": 238.595488,
    "max_profit_pips": 0,
    "max_loss_pips": 0,
    "reason": "Strong 2-min BEARISH signal (95.0% confidence)",
    "cycle_duration": 120,
    "ml_used": true,
    "ml_training_samples": 24,
    "volatility": 0.00015,
    "win_rate": 4.166666666666666,
    "git_pushed": false
  },
  {
    "id": "T16",
    "cycle": 4,
    "action": "SELL",
    "direction": "BEARISH",
    "entry_price": 1.1919,
    "entry_time": "2026-01-30T15:31:09.779720",
    "optimal_tp": 1.1911,
    "optimal_sl": 1.1924,
    "tp_distance_pips": 7,
    "sl_distance_pips": 4,
    "trade_size": 1000.0,
    "confidence": 67.77777777777779,
    "status": "CLOSED",
    "result": "PARTIAL_FAIL",
    "exit_price": 1.1919,
    "exit_time": "2026-01-30T15:35:09.347705",
    "exit_reason": "\u23f0 TIME ENDED at breakeven (TP NOT HIT)",
    "profit_pips": 0.0,
    "profit_amount": 0.0,
    "duration_seconds": 239.567972,
    "max_profit_pips": 0,
    "max_loss_pips": 0,
    "reason": "Strong 2-min BEARISH signal (67.8% confidence)",
    "cycle_duration": 120,
    "ml_used": true,
    "ml_training_samples": 25,
    "volatility": 0.00015,
    "win_rate": 4.0,
    "git_pushed": false
  },
  {
    "id": "T17",
    "cycle": 6,
    "action": "SELL",
    "direction": "BEARISH",
    "entry_price": 1.1919,
    "entry_time": "2026-01-30T15:35:10.567612",
    "optimal_tp": 1.1911,
    "optimal_sl": 1.1924,
    "tp_distance_pips": 7,
    "sl_distance_pips": 4,
    "trade_size": 1000.0,
    "confidence": 95.0,
    "status": "CLOSED",
    "result": "PARTIAL_FAIL",
    "exit_price": 1.1919,
    "exit_time": "2026-01-30T15:39:10.235823",
    "exit_reason": "\u23f0 TIME ENDED at breakeven (TP NOT HIT)",
    "profit_pips": 0.0,
    "profit_amount": 0.0,
    "duration_seconds": 239.668195,
    "max_profit_pips": 0,
    "max_loss_pips": 0,
    "reason": "Strong 2-min BEARISH signal (95.0% confidence)",
    "cycle_duration": 120,
    "ml_used": true,
    "ml_training_samples": 26,
    "volatility": 0.00015,
    "win_rate": 3.8461538461538463,
    "git_pushed": false
  },
  {
    "id": "T18",
    "cycle": 9,
    "action": "SELL",
    "direction": "BEARISH",
    "entry_price": 1.1919,
    "entry_time": "2026-01-30T15:41:10.246660",
    "optimal_tp": 1.1911,
    "optimal_sl": 1.1924,
    "tp_distance_pips": 7,
    "sl_distance_pips": 4,
    "trade_size": 1000.0,
    "confidence": 95.0,
    "status": "CLOSED",
    "result": "PARTIAL_FAIL",
    "exit_price": 1.1919,
    "exit_time": "2026-01-30T15:43:10.645375",
    "exit_reason": "\u23f0 TIME ENDED at breakeven (TP NOT HIT)",
    "profit_pips": 0.0,
    "profit_amount": 0.0,
    "duration_seconds": 120.398701,
    "max_profit_pips": 0,
    "max_loss_pips": 0,
    "reason": "Strong 2-min BEARISH signal (95.0% confidence)",
    "cycle_duration": 120,
    "ml_used": true,
    "ml_training_samples": 27,
    "volatility": 0.00015,
    "win_rate": 3.7037037037037033,
    "git_pushed": false
  }
]